alloys_props/__init__.py
alloys_props/formula.py
alloys_props/mendeleev_gw/__init__.py
alloys_props/mendeleev_gw/atoms_database.py
alloys_props/settings.py
alloys_props-0.1.1.dist-info/METADATA
alloys_props-0.1.1.dist-info/WHEEL
alloys_props-0.1.1.dist-info/RECORD
