Metadata-Version: 2.1
Name: alloys-props
Version: 0.1.1
Summary: Formula-based calculator for alloy properties
Author: abdoulfataoh
Author-email: abdoulfataoh@gmail.com
Requires-Python: >=3.10,<3.13
Classifier: Programming Language :: Python :: 3
Classifier: Programming Language :: Python :: 3.10
Classifier: Programming Language :: Python :: 3.11
Classifier: Programming Language :: Python :: 3.12
Requires-Dist: chempy (>=0.9.0,<0.10.0)
Requires-Dist: mendeleev (>=0.18.1,<0.19.0)
Requires-Dist: numpy (<2.0)
